VESIcal/__init__.py
VESIcal/activity_models.py
VESIcal/batchfile.py
VESIcal/batchmodel.py
VESIcal/calculate_classes.py
VESIcal/calibration_checks.py
VESIcal/calibrations.py
VESIcal/core.py
VESIcal/fugacity_models.py
VESIcal/model_classes.py
VESIcal/sample_class.py
VESIcal/vplot.py
VESIcal/models/__init__.py
VESIcal/models/allison.py
VESIcal/models/dixon.py
VESIcal/models/iaconomarziano.py
VESIcal/models/liu.py
VESIcal/models/magmasat.py
VESIcal/models/moore.py
VESIcal/models/shishkina.py
VESIcal/tasplot/__init__.py
VESIcal/tasplot/setup.py
VESIcal/thermo/__init__.py
VESIcal/thermo/densityx.py
VESIcal/thermo/giordano.py
VESIcal/thermo/thermo_calculate_classes.py
VESIcal/thermo/thermo_core.py
tests/__init__.py
tests/test_calculate.py
tests/test_importfile.py
tests/test_sample.py
VESIcal-1.2.5.dist-info/LICENSE
VESIcal-1.2.5.dist-info/METADATA
VESIcal-1.2.5.dist-info/WHEEL
VESIcal-1.2.5.dist-info/top_level.txt
VESIcal-1.2.5.dist-info/RECORD
