Metadata-Version: 2.1
Name: VESIcal
Version: 1.2.5
Summary: A generalized python library for calculating and plotting various things related to mixed volatile (H2O-CO2) solubility in silicate melts.
Home-page: https://github.com/kaylai/VESIcal
Author: Kayla Iacovino, Simon Matthews, Penny Wieser
Author-email: kaylaiacovino@gmail.com
License: UNKNOWN
Platform: UNKNOWN
Classifier: Programming Language :: Python :: 3
Classifier: License :: OSI Approved :: MIT License
Classifier: Operating System :: OS Independent
Requires-Python: >=3.6
License-File: LICENSE
Requires-Dist: pandas
Requires-Dist: numpy
Requires-Dist: matplotlib
Requires-Dist: scipy
Requires-Dist: sympy
Requires-Dist: openpyxl
